schnorrpy.cpython-35m-x86_64-linux-gnu.so
schnorrpy.so
schnorrpy.cpython-37m-x86_64-linux-gnu.so
schnorrpy.cpython-36m-x86_64-linux-gnu.so
schnorrpy-0.0.2.dist-info/METADATA
schnorrpy-0.0.2.dist-info/RECORD
schnorrpy-0.0.2.dist-info/top_level.txt
schnorrpy-0.0.2.dist-info/dependency_links.txt
schnorrpy-0.0.2.dist-info/WHEEL
