Metadata-Version: 2.1
Name: schnorrpy
Version: 0.0.2
Summary: A Python wrapper to the Rust schnorrkel SR25519 signature library.
Home-page: https://gitlab.com/kauriid/schnorrpy.git
Author: ['Mischa MacLeod', 'Guy K. Kloss']
Author-email: guy@mysinglesource.io
License: Apache License 2.0
Keywords: singlesource blockchain substrate centrality polkadot signing signature SS25519
Platform: UNKNOWN
Classifier: Development Status :: 3 - Alpha
Classifier: Intended Audience :: Developers
Classifier: Topic :: Utilities
Classifier: License :: OSI Approved :: Apache Software License
Classifier: Programming Language :: Python :: 3
Classifier: Programming Language :: Python :: 3.6
Classifier: Programming Language :: Python :: 3.7
